{"stem":"omnipoten","instances":[{"docId":"A001","docUri":"A001.html","score":2,"contexts":[{"form":"omnipotens","weight":"1","pos":341,"context":"...bono statu tuo, in quo te nobis conservet <mark>omnipotens<\/mark> deus, fili charme. ","fid":"text-letters"},{"form":"omnipotens","weight":"1","pos":661,"context":"...bono statu tuo, in quo te nobis conservet <mark>omnipotens<\/mark> deus, fili charme. ","fid":"text-letters"}]},{"docId":"A002","docUri":"A002.html","score":2,"contexts":[{"form":"omnipotens","weight":"1","pos":341,"context":"...bono statu tuo, in quo te nobis conservet <mark>omnipotens<\/mark> deus, fili charme. ","fid":"text-letters"},{"form":"omnipotens","weight":"1","pos":661,"context":"...bono statu tuo, in quo te nobis conservet <mark>omnipotens<\/mark> deus, fili charme. ","fid":"text-letters"}]}]}