{"stem":"the","instances":[{"docId":"A003","docUri":"A003.html","score":4,"contexts":[{"form":"the","weight":"1","pos":131,"context":"Ferdinand <mark>the<\/mark> Catholic promises F a successful hunting trip in the...","fid":"text-letters"},{"form":"the","weight":"1","pos":137,"context":"...the Catholic promises F a successful hunting trip in <mark>the<\/mark> future. His health.","fid":"text-letters"},{"form":"the","weight":"1","pos":322,"context":"Ferdinand <mark>the<\/mark> Catholic promises F a successful hunting trip in the...","fid":"text-letters"},{"form":"the","weight":"1","pos":328,"context":"...the Catholic promises F a successful hunting trip in <mark>the<\/mark> future. His health.","fid":"text-letters"}]}]}