{"stem":"25.000","instances":[{"docId":"A023","docUri":"A023.html","score":1,"contexts":[{"form":"25.000","weight":"1","pos":1070,"context":"...gerüsteten Gegner, am 18. Oktober den drei Fürsten <mark>25.000<\/mark> Gulden in drei Raten auszubezahlen. Ulmann, Fr....","fid":"letterContent"}]},{"docId":"A121a","docUri":"A121a.html","score":1,"contexts":[{"form":"25.000","weight":"1","pos":370,"context":"...Gulden sofort, in den nächsten zwei Jahren je <mark>25.000<\/mark> Gulden und in den folgenden zehn Jahren je 10.000...","fid":"letterContent"}]},{"docId":"A073","docUri":"A073.html","score":1,"contexts":[{"form":"25.000","weight":"1","pos":1333,"context":"...F’s mit der Forderung betreffs der ersten Rate von <mark>25.000<\/mark> Dukaten. Doch hielt man ihn mit der Anzahlung...","fid":"letterContent"}]}]}