{"stem":"311","instances":[{"docId":"A182","docUri":"A182.html","score":1,"contexts":[{"form":"311","weight":"1","pos":897,"context":"...S. 280, 292; Sanuto 39, 290, <mark>311<\/mark>, 314 u. a.","fid":"letterContent"}]},{"docId":"A023","docUri":"A023.html","score":1,"contexts":[{"form":"311","weight":"1","pos":1076,"context":"...auszubezahlen. Ulmann, Fr. von Sickinqen, S. <mark>311<\/mark>; Bremer, S. LXI.","fid":"letterContent"}]},{"docId":"A139","docUri":"A139.html","score":1,"contexts":[{"form":"311","weight":"1","pos":895,"context":"..., Hist. de la Représ. 1, S. <mark>311<\/mark> f.","fid":"letterContent"}]},{"docId":"A144","docUri":"A144.html","score":1,"contexts":[{"form":"311","weight":"1","pos":48,"context":"...Druck: Familienkorrespondenz Bd. 1, Nr. 144, S. <mark>311<\/mark>-312.","fid":"letterContent"}]},{"docId":"A076","docUri":"A076.html","score":1,"contexts":[{"form":"311","weight":"1","pos":15020,"context":"...geklagt. Balan, Mon. ref., S. <mark>311<\/mark> f. In dem übrigen Briefwechsel F’s mit dem Papst...","fid":"letterContent"}]},{"docId":"A143","docUri":"A143.html","score":1,"contexts":[{"form":"311","weight":"1","pos":224,"context":"...Familienkorrespondenz Bd. 1, Nr. 143, S. 305-<mark>311<\/mark>.","fid":"letterContent"}]}]}