{"stem":"angesetzten","instances":[{"docId":"A188","docUri":"A188.html","score":1,"contexts":[{"form":"angesetzten","weight":"1","pos":226,"context":"...zu bleiben und an dem für den 24. April <mark>angesetzten<\/mark> Landtag nicht teilzunehmen. M. H. H. 31, S....","fid":"letterContent"}]},{"docId":"A187","docUri":"A187.html","score":1,"contexts":[{"form":"angesetzten","weight":"1","pos":29,"context":"...zum Römischen Kg, Konzil, Hinausschiebung des für Speier <mark>angesetzten<\/mark> RT’s. 6. Bereit, nach Mailand zu gehen....","fid":"letterContent"}]}]}