{"stem":"asuré","instances":[{"docId":"A129","docUri":"A129.html","score":1,"contexts":[{"form":"asurée","weight":"1","pos":192,"context":"...,c) et vos affaires pour recomendés, soies toute <mark>asurée<\/mark>, mme, ma bone seur, que,...","fid":"letterContent"}]},{"docId":"A247","docUri":"A247.html","score":1,"contexts":[{"form":"asuré","weight":"1","pos":102,"context":"...desus entendu, et pour ce que ie suis <mark>asuré<\/mark> que, mme, seres bien aissé de savoir...","fid":"letterContent"}]}]}