{"stem":"ausgezahlt","instances":[{"docId":"A018","docUri":"A018.html","score":1,"contexts":[{"form":"ausgezahlt","weight":"1","pos":1135,"context":"...erstatten, warum er an zwei Personen keine Pensionen <mark>ausgezahlt<\/mark> hat und wer diese sind (Wien, H....","fid":"letterContent"}]},{"docId":"A076","docUri":"A076.html","score":1,"contexts":[{"form":"ausgezahlter","weight":"1","pos":86,"context":"...für das Regiment einwilligen. 14. Klagen wegen nicht <mark>ausgezahlter<\/mark> Pensionen. 15. Aufrichtung der Justiz und neuer Reichsämter...","fid":"letterContent"}]}]}