{"stem":"celebr","instances":[{"docId":"A166","docUri":"A166.html","score":1,"contexts":[{"form":"celebrer","weight":"1","pos":1061,"context":"...jours que suis arrivé en ceste ville pour y <mark>celebrer<\/mark> la diete imperiale , où il n’y a venuz...","fid":"letterContent"}]},{"docId":"A199","docUri":"A199.html","score":1,"contexts":[{"form":"celebrer","weight":"1","pos":87,"context":"...de Spire le 18e de ce mois pour y <mark>celebrer<\/mark> la diete . Pour les occasions que par mesd...","fid":"letterContent"}]},{"docId":"A088","docUri":"A088.html","score":1,"contexts":[{"form":"celebrer","weight":"1","pos":469,"context":"Touchant la prouchaine diete qui se doit <mark>celebrer<\/mark> à Spiere, si les lettres que vous ai,...","fid":"letterContent"}]},{"docId":"A164","docUri":"A164.html","score":1,"contexts":[{"form":"celebrer","weight":"1","pos":599,"context":"...poste est Ceville, où les nopces se debvoient <mark>celebrer<\/mark> que le mariage feust ja consommé. Je vous...","fid":"letterContent"}]}]}