{"stem":"commendacionem","instances":[{"docId":"A259","docUri":"A259.html","score":1,"contexts":[{"form":"commendacionem","weight":"1","pos":110,"context":"...tam graciosum se erga eum prestare, ut nostram <mark>commendacionem<\/mark> aliquid commodi sibi attulisse senciat. ","fid":"letterContent"}]},{"docId":"A258","docUri":"A258.html","score":1,"contexts":[{"form":"commendacionem","weight":"1","pos":67,"context":"...nostri, domini comites regni Croacie , ut in <mark>commendacionem<\/mark> egregii Joannis Perwsyth et Gasparis Crysenyth ad M tem...","fid":"letterContent"}]}]}