{"stem":"conatui","instances":[{"docId":"A049","docUri":"A049.html","score":2,"contexts":[{"form":"conatui","weight":"1","pos":79,"context":"...quo tamen interim presenti illi malo tantoque perfidissimorum hostium <mark>conatui<\/mark> obvietur, Sertem Vram non modo admonendam, sed...","fid":"letterContent"},{"form":"conatui","weight":"1","pos":228,"context":"...quo tamen interim presenti illi malo tantoque perfidissimorum hostium <mark>conatui<\/mark> obvietur, Sertem Vram non modo admonendam, sed...","fid":"letterContent"}]}]}