{"stem":"constituatur","instances":[{"docId":"A175","docUri":"A175.html","score":1,"contexts":[{"form":"constituatur","weight":"1","pos":419,"context":"...quietior, solidior et constantior semel Italicarum rerum status <mark>constituatur<\/mark> maxime circa gubernium et conservationem ducatus et status Mediolani...","fid":"letterContent"}]},{"docId":"A076","docUri":"A076.html","score":1,"contexts":[{"form":"constituatur","weight":"1","pos":15171,"context":"...eciam, priusquam agatur de rege Romanorum, princeps <mark>constituatur<\/mark> locumtenens Italiẹ.“ Schließlich meinte der Papst von F....","fid":"letterContent"}]}]}