{"stem":"convenabl","instances":[{"docId":"A142","docUri":"A142.html","score":1,"contexts":[{"form":"convenablement","weight":"1","pos":682,"context":"...dict de ma part et à tout vouliez pourveoir <mark>convenablement<\/mark>, et si mon advis estoit d’accepter, il...","fid":"letterContent"}]},{"docId":"A239","docUri":"A239.html","score":1,"contexts":[{"form":"convenablement","weight":"1","pos":3801,"context":"a1) in W1 folgt bien briefvement et <mark>convenablement<\/mark> pourveu et remedié.","fid":"letterContent"}]},{"docId":"A250","docUri":"A250.html","score":1,"contexts":[{"form":"convenablement","weight":"1","pos":206,"context":"..., si dieu et les princes christiens n’y remedient <mark>convenablement<\/mark>, le dangier, enquoi le tout est....","fid":"letterContent"}]}]}