{"stem":"darstellung","instances":[{"docId":"A076","docUri":"A076.html","score":2,"contexts":[{"form":"Darstellung","weight":"1","pos":14911,"context":"bis 13] Hier wird eine historische <mark>Darstellung<\/mark> der Reichsregiments- und Kammergerichtsfrage zu geben versucht....","fid":"letterContent"},{"form":"Darstellung","weight":"1","pos":15454,"context":"und 59] Vgl. die <mark>Darstellung<\/mark> in Nr. A65, A72.","fid":"letterContent"}]},{"docId":"A070","docUri":"A070.html","score":1,"contexts":[{"form":"Darstellung","weight":"1","pos":609,"context":"F gibt hier eine ausführliche <mark>Darstellung<\/mark> seiner Verhandlung mit den Ständen, um die Vermittlungsgesandtschaft...","fid":"letterContent"}]}]}