{"stem":"dedan","instances":[{"docId":"380413FM_Vortrag_2022_11","docUri":"380413FM_Vortrag_2022_11.html","score":3,"contexts":[{"form":"dedans","weight":"1","pos":296,"context":"...morut, et lae) fis ouvrir et trovay <mark>dedans<\/mark> ung grant boulet f)come d’estatf) casy [=...","fid":"letterContent"},{"form":"dedans","weight":"1","pos":319,"context":"...] et cassy de la mesme taille. Mes <mark>dedans<\/mark> estoit come ung ugnon [= oignon] tout par...","fid":"letterContent"},{"form":"dedans","weight":"1","pos":340,"context":"...matiere come de euf [= œuf] dur et <mark>dedans<\/mark> ungne grande pice [= pièce] ronde come ung...","fid":"letterContent"}]}]}