{"stem":"ess","instances":[{"docId":"380522KF_Vortrag_2022_11","docUri":"380522KF_Vortrag_2022_11.html","score":1,"contexts":[{"form":"esse","weight":"1","pos":253,"context":"...nostro nomine dirigere et, si quid per nos prestandum <mark>esse<\/mark> judicaverit, nos reddere certiores, ut iuxta Vestrae...","fid":"letterContent"}]},{"docId":"380801FKb_Vortrag_2022_11","docUri":"380801FKb_Vortrag_2022_11.html","score":1,"contexts":[{"form":"ess","weight":"1","pos":351,"context":"...lugar a que un collegio tan insigne como aquel <mark>ess<\/mark>) reciba semejante lesión y detrimento por ningún respecto...","fid":"letterContent"}]}]}