{"stem":"furni","instances":[{"docId":"A139","docUri":"A139.html","score":1,"contexts":[{"form":"furni","weight":"1","pos":307,"context":"...pour laquelle furnir. Je ne suis trop bien <mark>furni<\/mark> pour les causes que par-ci-devant vous ai...","fid":"letterContent"}]},{"docId":"A121b","docUri":"A121b.html","score":1,"contexts":[{"form":"furni","weight":"1","pos":530,"context":"...entendu que la somme de deniers que monsr a <mark>furni<\/mark> aux pietons que le feu comte de Sornes mena...","fid":"letterContent"}]},{"docId":"A026","docUri":"A026.html","score":1,"contexts":[{"form":"furni","weight":"1","pos":2697,"context":"...April schreibt: Pour vous obeir eusse je voulontiers <mark>furni<\/mark> à l’envoi de deux conseilleurs de vostre part au...","fid":"letterContent"}]}]}