{"stem":"gagner","instances":[{"docId":"A252","docUri":"A252.html","score":1,"contexts":[{"form":"gagner","weight":"1","pos":777,"context":"...) faire appoinctement avec le roi de France, <mark>gagner<\/mark> le plus d’alliéz que pourrai et tacher de rompre...","fid":"letterContent"}]},{"docId":"A239","docUri":"A239.html","score":1,"contexts":[{"form":"gagner","weight":"1","pos":730,"context":"...et semblablement tacher et practiquer par tous moyens pour <mark>gagner<\/mark> à vostre devotion le plus des alliéz que pourrez...","fid":"letterContent"}]},{"docId":"A143","docUri":"A143.html","score":1,"contexts":[{"form":"gagner","weight":"1","pos":398,"context":"...de quoi je vous veulx et pourrai aider pour <mark>gagner<\/mark> les electeurs en lad. election, je vous...","fid":"letterContent"}]}]}