{"stem":"gén","instances":[{"docId":"A231","docUri":"A231.html","score":1,"contexts":[{"form":"gén","weight":"1","pos":116,"context":"Brüssel, Arch. <mark>gén<\/mark>. Papiers de l’État et de lʼAud., vol...","fid":"letterContent"}]},{"docId":"A228","docUri":"A228.html","score":1,"contexts":[{"form":"gén","weight":"1","pos":31,"context":"Brüssel, Arch. <mark>gén<\/mark>. Papiers de l’État et de l’Aud., vol...","fid":"letterContent"}]},{"docId":"A158","docUri":"A158.html","score":1,"contexts":[{"form":"gén","weight":"1","pos":217,"context":"(B) Brüssel. Arch. <mark>gén<\/mark>. Pap. de lʼÉtat et de l’Aud.,...","fid":"letterContent"}]},{"docId":"A223","docUri":"A223.html","score":1,"contexts":[{"form":"gén","weight":"1","pos":55,"context":"Brüssel, Arch. <mark>gén<\/mark>. Pap. de l’État et de lʼAud.,...","fid":"letterContent"}]},{"docId":"A221","docUri":"A221.html","score":1,"contexts":[{"form":"gén","weight":"1","pos":67,"context":"Brüssel, Arch. <mark>gén<\/mark>. Papiers de l’État et de lʼAud., vol...","fid":"letterContent"}]},{"docId":"A241","docUri":"A241.html","score":1,"contexts":[{"form":"gén","weight":"1","pos":63,"context":"Brüssel, Arch. <mark>gén<\/mark>. Papiers de l’État et de l’Aud., vol...","fid":"letterContent"}]},{"docId":"A069","docUri":"A069.html","score":1,"contexts":[{"form":"gén","weight":"1","pos":89,"context":"(B.) aus Brüssel, Arch. <mark>gén<\/mark>. Pap. de l’Etat et de l’Aud....","fid":"letterContent"}]},{"docId":"A100","docUri":"A100.html","score":1,"contexts":[{"form":"gén","weight":"1","pos":80,"context":"(B) Brüssel. Arch. <mark>gén<\/mark>. Pap. de l'État et de lʼAud....","fid":"letterContent"}]},{"docId":"A153","docUri":"A153.html","score":1,"contexts":[{"form":"gén","weight":"1","pos":41,"context":"Brüssel, Arch. <mark>gén<\/mark>. Papiers de lʼÉtat et de lʼAudience, vol...","fid":"letterContent"}]},{"docId":"A154","docUri":"A154.html","score":1,"contexts":[{"form":"gén","weight":"1","pos":32,"context":"Brüssel. Arch. <mark>gén<\/mark>. Papiers de l’État et de l’Aud., vol...","fid":"letterContent"}]},{"docId":"A063","docUri":"A063.html","score":1,"contexts":[{"form":"Gén","weight":"1","pos":789,"context":"...tourneroit sur , et . Brüssel, Arch. <mark>Gén<\/mark>. Sécret, de lʼÉt. Allem. Diètes II....","fid":"letterContent"}]},{"docId":"A090","docUri":"A090.html","score":1,"contexts":[{"form":"Gén","weight":"1","pos":72,"context":"(B) Brüssel, Arch. <mark>Gén<\/mark>. Pap. de l’État et ele lʼAud.,...","fid":"letterContent"}]},{"docId":"A211","docUri":"A211.html","score":1,"contexts":[{"form":"gén","weight":"1","pos":23,"context":"Brüssel, Arch. <mark>gén<\/mark>. Papiers de l’État et de I'Aud., vol...","fid":"letterContent"}]},{"docId":"A240","docUri":"A240.html","score":1,"contexts":[{"form":"gén","weight":"1","pos":34,"context":"Brüssel, Arch. <mark>gén<\/mark>. Papiers de l’État et de l’Aud., vol...","fid":"letterContent"}]},{"docId":"A252","docUri":"A252.html","score":1,"contexts":[{"form":"gén","weight":"1","pos":232,"context":"(B) Brüssel, Arch. <mark>gén<\/mark>. Papiers de lʼEtat et de lʼAud. vol...","fid":"letterContent"}]},{"docId":"A198","docUri":"A198.html","score":1,"contexts":[{"form":"gén","weight":"1","pos":42,"context":"Brüssel, Arch. <mark>gén<\/mark>. Papiers de lʼÉtat et de lʼAud., vol...","fid":"letterContent"}]},{"docId":"A215","docUri":"A215.html","score":1,"contexts":[{"form":"gén","weight":"1","pos":112,"context":"Brüssel, Arch. <mark>gén<\/mark>. Papiers de l’État et de lʼAud. vol...","fid":"letterContent"}]},{"docId":"A222","docUri":"A222.html","score":1,"contexts":[{"form":"gén","weight":"1","pos":39,"context":"Brüssel, Arch. <mark>gén<\/mark>. Papiers de l’État et de lʼAud., vol...","fid":"letterContent"}]},{"docId":"A183","docUri":"A183.html","score":1,"contexts":[{"form":"Gén","weight":"1","pos":52,"context":"Brüssel, Arch. <mark>Gén<\/mark>. Papiers de l'État et de lʼAud., vol...","fid":"letterContent"}]},{"docId":"A238","docUri":"A238.html","score":1,"contexts":[{"form":"gén","weight":"1","pos":139,"context":"Brüssel, Arch. <mark>gén<\/mark>. Papiers de l’État et de l’Aud., vol...","fid":"letterContent"}]},{"docId":"A081","docUri":"A081.html","score":1,"contexts":[{"form":"gén","weight":"1","pos":97,"context":"(B.) Brüssel. Archives <mark>gén<\/mark>. Pap. de l’État et de l’Aud.,...","fid":"letterContent"}]},{"docId":"A237","docUri":"A237.html","score":1,"contexts":[{"form":"gén","weight":"1","pos":58,"context":"Brüssel, Arch. <mark>gén<\/mark>. Papiers de l’État et de l’Aud., vol...","fid":"letterContent"}]},{"docId":"A242","docUri":"A242.html","score":1,"contexts":[{"form":"gén","weight":"1","pos":116,"context":"Brüssel, Arch. <mark>gén<\/mark>. Papiers de lʼÉtat et de lʼAud., vol...","fid":"letterContent"}]},{"docId":"A089","docUri":"A089.html","score":1,"contexts":[{"form":"Gén","weight":"1","pos":132,"context":"(B) Brüssel. Arch. <mark>Gén<\/mark>. Papiers de l’État et de l'Aud. vol...","fid":"letterContent"}]},{"docId":"A217","docUri":"A217.html","score":1,"contexts":[{"form":"gén","weight":"1","pos":102,"context":"Brüssel, Arch. <mark>gén<\/mark>. Papiers de l'État et de l’Aud., vol...","fid":"letterContent"}]},{"docId":"A207","docUri":"A207.html","score":1,"contexts":[{"form":"gén","weight":"1","pos":87,"context":"Brüssel, Arch. <mark>gén<\/mark>. Papiers de l'État et de lʼAud., vol...","fid":"letterContent"}]},{"docId":"A072","docUri":"A072.html","score":1,"contexts":[{"form":"gén","weight":"1","pos":858,"context":"...es zwei Breschen erhalten hatte. Brüssel, Arch. <mark>gén<\/mark>. Secret. de l'Ét. et de lʼAud...","fid":"letterContent"}]},{"docId":"A167","docUri":"A167.html","score":1,"contexts":[{"form":"gén","weight":"1","pos":71,"context":"(B) Brüssel, Arch. <mark>gén<\/mark>. Papiers d’État et de lʼAud., vol....","fid":"letterContent"}]},{"docId":"A212","docUri":"A212.html","score":1,"contexts":[{"form":"gén","weight":"1","pos":53,"context":"Brüssel, Arch. <mark>gén<\/mark>. Papiers de l'État et de l’Aud., vol...","fid":"letterContent"}]},{"docId":"A244","docUri":"A244.html","score":1,"contexts":[{"form":"gén","weight":"1","pos":80,"context":"Brüssel, Arch. <mark>gén<\/mark>. Papiers de lʼÉtat et de l'Aud., vol...","fid":"letterContent"}]},{"docId":"A209","docUri":"A209.html","score":1,"contexts":[{"form":"gén","weight":"1","pos":24,"context":"Brüssel, Arch. <mark>gén<\/mark>. Papiers de LʼÉtat et de l’Aud., vol...","fid":"letterContent"}]},{"docId":"A191","docUri":"A191.html","score":1,"contexts":[{"form":"Gén","weight":"1","pos":35,"context":"Brüssel, Arch. <mark>Gén<\/mark>. Papiers de l’État et de l'Aud. vol...","fid":"letterContent"}]},{"docId":"A117","docUri":"A117.html","score":1,"contexts":[{"form":"gén","weight":"1","pos":108,"context":"(B) Brüssel, Arch. <mark>gén<\/mark>. Pap. de l’État et de lʼAudience vol...","fid":"letterContent"}]},{"docId":"A162","docUri":"A162.html","score":1,"contexts":[{"form":"gén","weight":"1","pos":65,"context":"Brüssel. Arch. <mark>gén<\/mark>. Papiers de lʼÉtat et de lʼAud. Vol...","fid":"letterContent"}]},{"docId":"A254","docUri":"A254.html","score":1,"contexts":[{"form":"gén","weight":"1","pos":102,"context":"Brüssel, Arch. <mark>gén<\/mark>. Papiers de lʼÉtat et de lʼAud., vol...","fid":"letterContent"}]},{"docId":"A224","docUri":"A224.html","score":1,"contexts":[{"form":"gén","weight":"1","pos":34,"context":"Brüssel, Arch. <mark>gén<\/mark>. Papiers de lʼÉtat et de lʼAud., vol...","fid":"letterContent"}]},{"docId":"A195","docUri":"A195.html","score":1,"contexts":[{"form":"gén","weight":"1","pos":36,"context":"Brüssel, Arch. <mark>gén<\/mark>. Papiers de l’État et de lʼAud., vol...","fid":"letterContent"}]},{"docId":"A205","docUri":"A205.html","score":1,"contexts":[{"form":"gén","weight":"1","pos":88,"context":"Brüssel, Arch. <mark>gén<\/mark>. Papiers de l’État et de l'Aud., vol...","fid":"letterContent"}]},{"docId":"A214","docUri":"A214.html","score":1,"contexts":[{"form":"gén","weight":"1","pos":23,"context":"Brüssel, Arch. <mark>gén<\/mark>. Papiers de l’État et de l’Aud. vol...","fid":"letterContent"}]},{"docId":"A220","docUri":"A220.html","score":1,"contexts":[{"form":"gén","weight":"1","pos":79,"context":"Brüssel. Arch. <mark>gén<\/mark>. Papiers de lʼÉtat et de l’Aud. Vol...","fid":"letterContent"}]},{"docId":"A178","docUri":"A178.html","score":1,"contexts":[{"form":"gén","weight":"1","pos":54,"context":"Brüssel, Arch. <mark>gén<\/mark>. Papiers de lʼÉtat et de l’Aud., vol...","fid":"letterContent"}]},{"docId":"A062","docUri":"A062.html","score":1,"contexts":[{"form":"gén","weight":"1","pos":265,"context":"(B.) Brüssel, Arch. <mark>gén<\/mark>. Pap. de l'État et de lʼAudience vol...","fid":"letterContent"}]},{"docId":"A083","docUri":"A083.html","score":1,"contexts":[{"form":"gén","weight":"1","pos":70,"context":"(B.) Brüssel. Arch. <mark>gén<\/mark>. Pap. de lʼÉtat et de lʼAud....","fid":"letterContent"}]},{"docId":"A206","docUri":"A206.html","score":1,"contexts":[{"form":"gén","weight":"1","pos":36,"context":"Brüssel, Arch. <mark>gén<\/mark>. Papiers de lʼÉtat et de lʼAud., vol...","fid":"letterContent"}]},{"docId":"A056","docUri":"A056.html","score":1,"contexts":[{"form":"gén","weight":"1","pos":136,"context":"(B.) Brüssel, Coll. Arch. <mark>gén<\/mark>. Papiers de l’Etat et d’Audience. 43, Bl....","fid":"letterContent"}]},{"docId":"A164","docUri":"A164.html","score":1,"contexts":[{"form":"gén","weight":"1","pos":97,"context":"Brüssel, Arch. <mark>gén<\/mark>. Papiers de l'État et de lʼAud., vol...","fid":"letterContent"}]}]}