{"stem":"haze","instances":[{"docId":"A136","docUri":"A136.html","score":4,"contexts":[{"form":"haze","weight":"1","pos":522,"context":"...de otra tan grande y que muy mayor la <mark>haze<\/mark> haberla Su Md conseguido sin ayuda ni favor de...","fid":"letterContent"},{"form":"haze","weight":"1","pos":2374,"context":"...costa que asta aquí Su A ha echo y <mark>haze<\/mark>, asi en la guerra de Ytalia , y...","fid":"letterContent"},{"form":"haze","weight":"1","pos":2528,"context":"...pero el deseo que á su servicio tiene le <mark>haze<\/mark> dezir, que se acuerde de las alteraciones de...","fid":"letterContent"},{"form":"haze","weight":"1","pos":2588,"context":"...que no dispornia del, lo qual Su A <mark>haze<\/mark> saber al enperador, no para otro efeto,...","fid":"letterContent"}]},{"docId":"A140","docUri":"A140.html","score":1,"contexts":[{"form":"haze","weight":"1","pos":543,"context":"Iten como Su A ha echo y <mark>haze<\/mark> todas las provisiones posibles asi en dar á la...","fid":"letterContent"}]},{"docId":"A008","docUri":"A008.html","score":1,"contexts":[{"form":"haze","weight":"1","pos":542,"context":"...tengays por bueno esto y creyais que todo se <mark>haze<\/mark> por vuestro bien, y vos acordeys siempre del...","fid":"letterContent"}]}]}