{"stem":"iisdem","instances":[{"docId":"A076","docUri":"A076.html","score":1,"contexts":[{"form":"iisdem","weight":"1","pos":7539,"context":"...expositum maximis curis, laboribus multisque ac variis atque <mark>iisdem<\/mark> fere inutilibus impensis administrandum, quia constat nobis Mtis...","fid":"letterContent"}]},{"docId":"A065","docUri":"A065.html","score":1,"contexts":[{"form":"iisdem","weight":"1","pos":424,"context":"...non ignoro sacram Mtem Vram esse multis variisque et <mark>iisdem<\/mark> maximis et gravissimis negociis impeditam et adeo iam bellicis...","fid":"letterContent"}]}]}