{"stem":"johanna","instances":[{"docId":"listperson","docUri":"listperson.html","score":2,"contexts":[{"form":"Johanna","weight":"1","pos":9616,"context":"<mark>Johanna<\/mark> von Kastilien, Gattin Philipps I. („des Schönen“),...","fid":"tocTable"},{"form":"Johanna","weight":"1","pos":9621,"context":"...Kastilien, Gattin Philipps I. („des Schönen“), „<mark>Johanna<\/mark> die Wahnsinnige“, Königin von Kastilien (1504-...","fid":"tocTable"}]},{"docId":"A001","docUri":"A001.html","score":1,"contexts":[{"form":"Johanna","weight":"1","pos":270,"context":"...den Katholischen, an die Königin Germaine und an <mark>Johanna<\/mark> von Kastilien.","fid":"d5e139"}]}]}