{"stem":"l'appel","instances":[{"docId":"A164","docUri":"A164.html","score":2,"contexts":[{"form":"l’appelation","weight":"1","pos":149,"context":"...avez donné à la renunciation etd) abolition de <mark>l’appelation<\/mark> que ung bourgeois de Maastricht avoit interjetté d’une sentence...","fid":"letterContent"},{"form":"l’appelation","weight":"1","pos":208,"context":"...ce qu’ilf) entendroit l’empereur et ferez dire de <mark>l’appelation<\/mark> il se rangaste à la raison.","fid":"letterContent"}]},{"docId":"A220","docUri":"A220.html","score":1,"contexts":[{"form":"l’appellation","weight":"1","pos":101,"context":"...Kesselt, sur la rompture des Veneciens et de <mark>l’appellation<\/mark> d’Utrecht aussi de leur ... ","fid":"letterContent"}]}]}