{"stem":"laeken","instances":[{"docId":"listperson","docUri":"listperson.html","score":20,"contexts":[{"form":"Laeken","weight":"1","pos":256,"context":"Margareta an Ferdinand, 1526 September 20, <mark>Laeken<\/mark>.","fid":"tocTable"},{"form":"Laeken","weight":"1","pos":597,"context":"Margareta an Ferdinand, 1526 September 20, <mark>Laeken<\/mark>.","fid":"tocTable"},{"form":"Laeken","weight":"1","pos":1878,"context":"Margareta an Ferdinand, 1526 September 20, <mark>Laeken<\/mark>.","fid":"tocTable"},{"form":"Laeken","weight":"1","pos":1883,"context":"Margareta an Ferdinand, 1526 September 20, <mark>Laeken<\/mark>.","fid":"tocTable"},{"form":"Laeken","weight":"1","pos":1888,"context":"Margareta an Ferdinand, 1526 September 20, <mark>Laeken<\/mark>.","fid":"tocTable"},{"form":"Laeken","weight":"1","pos":1893,"context":"Margareta an Ferdinand, 1526 September 20, <mark>Laeken<\/mark>.","fid":"tocTable"},{"form":"Laeken","weight":"1","pos":1898,"context":"Margareta an Ferdinand, 1526 September 20, <mark>Laeken<\/mark>.","fid":"tocTable"},{"form":"Laeken","weight":"1","pos":2499,"context":"Margareta an Ferdinand, 1526 September 20, <mark>Laeken<\/mark>.","fid":"tocTable"},{"form":"Laeken","weight":"1","pos":2696,"context":"Margareta an Ferdinand, 1526 September 20, <mark>Laeken<\/mark>.","fid":"tocTable"},{"form":"Laeken","weight":"1","pos":2701,"context":"Margareta an Ferdinand, 1526 September 20, <mark>Laeken<\/mark>.","fid":"tocTable"},{"form":"Laeken","weight":"1","pos":3332,"context":"Margareta an Ferdinand, 1526 September 20, <mark>Laeken<\/mark>.","fid":"tocTable"},{"form":"Laeken","weight":"1","pos":3510,"context":"Margareta an Ferdinand, 1526 September 20, <mark>Laeken<\/mark>.","fid":"tocTable"},{"form":"Laeken","weight":"1","pos":3515,"context":"Margareta an Ferdinand, 1526 September 20, <mark>Laeken<\/mark>.","fid":"tocTable"},{"form":"Laeken","weight":"1","pos":3751,"context":"Margareta an Ferdinand, 1526 September 20, <mark>Laeken<\/mark>.","fid":"tocTable"},{"form":"Laeken","weight":"1","pos":3869,"context":"Margareta an Ferdinand, 1526 September 20, <mark>Laeken<\/mark>.","fid":"tocTable"},{"form":"Laeken","weight":"1","pos":4184,"context":"Margareta an Ferdinand, 1526 September 20, <mark>Laeken<\/mark>.","fid":"tocTable"},{"form":"Laeken","weight":"1","pos":4189,"context":"Margareta an Ferdinand, 1526 September 20, <mark>Laeken<\/mark>.","fid":"tocTable"},{"form":"Laeken","weight":"1","pos":6559,"context":"Margareta an Ferdinand, 1526 September 20, <mark>Laeken<\/mark>.","fid":"tocTable"},{"form":"Laeken","weight":"1","pos":6564,"context":"Margareta an Ferdinand, 1526 September 20, <mark>Laeken<\/mark>.","fid":"tocTable"},{"form":"Laeken","weight":"1","pos":6590,"context":"Margareta an Ferdinand, 1526 September 20, <mark>Laeken<\/mark>.","fid":"tocTable"}]},{"docId":"listplace","docUri":"listplace.html","score":8,"contexts":[{"form":"Laeken","weight":"1","pos":531,"context":"Margareta an Ferdinand, 1526 September 20, <mark>Laeken<\/mark>.","fid":"tocTable"},{"form":"Laeken","weight":"1","pos":1181,"context":"Margareta an Ferdinand, 1526 September 20, <mark>Laeken<\/mark>.","fid":"tocTable"},{"form":"Laeken","weight":"1","pos":2074,"context":"Margareta an Ferdinand, 1526 September 20, <mark>Laeken<\/mark>.","fid":"tocTable"},{"form":"Laeken","weight":"1","pos":2085,"context":"Margareta an Ferdinand, 1526 September 20, <mark>Laeken<\/mark>.","fid":"tocTable"},{"form":"Laeken","weight":"1","pos":2106,"context":"Margareta an Ferdinand, 1526 September 20, <mark>Laeken<\/mark>.","fid":"tocTable"},{"form":"Laeken","weight":"1","pos":2112,"context":"Margareta an Ferdinand, 1526 September 20, <mark>Laeken<\/mark>.","fid":"tocTable"},{"form":"Laeken","weight":"1","pos":2113,"context":"<mark>Laeken<\/mark>","fid":"tocTable"},{"form":"Laeken","weight":"1","pos":2118,"context":"Margareta an Ferdinand, 1526 September 20, <mark>Laeken<\/mark>.","fid":"tocTable"}]}]}