{"stem":"maestà","instances":[{"docId":"A087","docUri":"A087.html","score":1,"contexts":[{"form":"maestà","weight":"1","pos":312,"context":"...: La serenità del principe have scritto a questa <mark>maestà<\/mark>, di voler mandar qui Andrea de Burgo per...","fid":"letterContent"}]},{"docId":"A175","docUri":"A175.html","score":1,"contexts":[{"form":"maestà","weight":"1","pos":1700,"context":"...da 1’archiduca in posta per rechieder a questa <mark>maestà<\/mark> Milan, zoè il stado dil ducha, over...","fid":"letterContent"}]}]}