{"stem":"najera","instances":[{"docId":"A050","docUri":"A050.html","score":1,"contexts":[{"form":"Najera","weight":"1","pos":3347,"context":"Vermutlich ist unter Matarra der Abt <mark>Najera<\/mark> gemeint.","fid":"letterContent"}]},{"docId":"A046","docUri":"A046.html","score":1,"contexts":[{"form":"Najera","weight":"1","pos":316,"context":"...je doiz fournir à Genesve, et l’abbé de <mark>Najera<\/mark> fournira à tout ce que reste à payer....","fid":"letterContent"}]},{"docId":"A047","docUri":"A047.html","score":1,"contexts":[{"form":"Najera","weight":"1","pos":704,"context":"...Mann reichende Geld auszahle, denn der Abt von <mark>Najera<\/mark> werde davon 18.000 und der Schatzmeister 9000 Dukaten zurückerstatten...","fid":"letterContent"}]}]}