{"stem":"negotiorum","instances":[{"docId":"A173","docUri":"A173.html","score":1,"contexts":[{"form":"negotiorum","weight":"1","pos":204,"context":"...liberius inseruntur oratorumque fidei et ingenio ex rerum et <mark>negotiorum<\/mark> statu et variatione tractanda seorsum tutius commituntur. Alia...","fid":"letterContent"}]},{"docId":"A076","docUri":"A076.html","score":1,"contexts":[{"form":"negotiorum","weight":"1","pos":2900,"context":"Prẹterea <mark>negotiorum<\/mark> ipsa tractatio difficultasque ac simul varia practica in ipso...","fid":"letterContent"}]},{"docId":"A175","docUri":"A175.html","score":1,"contexts":[{"form":"negotiorum","weight":"1","pos":1055,"context":"...in prẹmissorum tractatione intervenerint, iuxta exigentiam et qualitatem <mark>negotiorum<\/mark>, vigore prẹsentis mandati acceperit et sustinuerit, dolo...","fid":"letterContent"}]}]}