{"stem":"posta","instances":[{"docId":"A136","docUri":"A136.html","score":3,"contexts":[{"form":"postas","weight":"1","pos":538,"context":"Iten como por las <mark>postas<\/mark> pasadas y con Meneses se le ha escripto dezir...","fid":"letterContent"},{"form":"posta","weight":"1","pos":553,"context":"...ha servido en esta enpresa, veniendo como por <mark>posta<\/mark> otro dia, que supo la nueva de la...","fid":"letterContent"},{"form":"posta","weight":"1","pos":751,"context":"...que estaba en esta villa con carros casi por <mark>posta<\/mark>.","fid":"letterContent"}]},{"docId":"A008","docUri":"A008.html","score":2,"contexts":[{"form":"posta","weight":"1","pos":148,"context":"...fuimos largamente certificado por letras que me truxó una <mark>posta<\/mark> en el mes de agosto passado y dicho y...","fid":"letterContent"},{"form":"postas","weight":"1","pos":209,"context":".... Agora por diversas cartas que con las dos <mark>postas<\/mark> postreras reciví, hé sido informado que aquello passa...","fid":"letterContent"}]},{"docId":"A175","docUri":"A175.html","score":1,"contexts":[{"form":"posta","weight":"1","pos":1697,"context":"...la corte di qui mandato da 1’archiduca in <mark>posta<\/mark> per rechieder a questa maestà Milan, zoè il...","fid":"letterContent"}]}]}