{"stem":"prolixior","instances":[{"docId":"A065","docUri":"A065.html","score":1,"contexts":[{"form":"prolixior","weight":"1","pos":3277,"context":"...prorogationis huius conventus causẹ, quas tamen, ne <mark>prolixior<\/mark> sim, hic reseco, Mtem Vram tanquam dominum...","fid":"letterContent"}]},{"docId":"A066","docUri":"A066.html","score":1,"contexts":[{"form":"prolixiores","weight":"1","pos":1357,"context":"a) <mark>prolixiores<\/mark> literas W1. - b) exceptoque eo, qua decebat ob...","fid":"letterContent"}]}]}