{"stem":"reliquum","instances":[{"docId":"A202","docUri":"A202.html","score":1,"contexts":[{"form":"Reliquum","weight":"1","pos":390,"context":"<mark>Reliquum<\/mark> est, ut Sertem Vram iterum quam diligenter admonitam...","fid":"letterContent"}]},{"docId":"380522KF_Vortrag_2022_11","docUri":"380522KF_Vortrag_2022_11.html","score":1,"contexts":[{"form":"reliquum","weight":"1","pos":222,"context":"...Serenitati Vestrae hic inclusum mittimus, in quibus etiam <mark>reliquum<\/mark> istius negotii ad Vestram Serenitatem remisimus Serenitatem Vestram fraterne...","fid":"letterContent"}]}]}