{"stem":"sanctam","instances":[{"docId":"A076","docUri":"A076.html","score":1,"contexts":[{"form":"sanctam","weight":"1","pos":4120,"context":"...rapitur, charitatis prẹtextu imponitur. Persuasum habet iam <mark>sanctam<\/mark> sedem Rhomanam Babylonem illam esse omnium scelerum et flagitiorum...","fid":"letterContent"}]},{"docId":"A080","docUri":"A080.html","score":1,"contexts":[{"form":"sanctam","weight":"1","pos":1161,"context":"...commisimus, per illum, qui nobis hanc tam <mark>sanctam<\/mark> ecclesiam tam immaculatam sponsam suam reliquit, qui tanta...","fid":"letterContent"}]}]}