{"stem":"schönberg","instances":[{"docId":"A071","docUri":"A071.html","score":1,"contexts":[{"form":"Schönberg","weight":"1","pos":254,"context":"...Die Sendung des EB von Kapua, Nikolaus von <mark>Schönberg<\/mark>, zum Kaiser usw. wird bereits in Nr....","fid":"letterContent"}]},{"docId":"A089","docUri":"A089.html","score":1,"contexts":[{"form":"Schönberg","weight":"1","pos":807,"context":"...September brach der Eb von Kapua (Nikolaus von <mark>Schönberg<\/mark>) von Rom auf, um die Kge von Frankreich...","fid":"letterContent"}]},{"docId":"A131","docUri":"A131.html","score":1,"contexts":[{"form":"Schönberg","weight":"1","pos":854,"context":"...besonders auf die von Frundsberg erbeuteten Koffer Dietrichs von <mark>Schönberg<\/mark> hinzuweisen, die Papiere enthielten, welche die Beziehungen...","fid":"letterContent"}]},{"docId":"A069","docUri":"A069.html","score":1,"contexts":[{"form":"Schönberg","weight":"1","pos":790,"context":"...— EB von Kapua war der Dominikaner Nikolaus von <mark>Schönberg<\/mark>, der am 11. März von Rom abreiste und...","fid":"letterContent"}]}]}