{"stem":"sedem","instances":[{"docId":"A076","docUri":"A076.html","score":2,"contexts":[{"form":"sedem","weight":"1","pos":4121,"context":"..., charitatis prẹtextu imponitur. Persuasum habet iam sanctam <mark>sedem<\/mark> Rhomanam Babylonem illam esse omnium scelerum et flagitiorum teterrimam...","fid":"letterContent"},{"form":"sedem","weight":"1","pos":5371,"context":"...pristina affectione deflectit, cuius tamen maiores fervore magno <mark>sedem<\/mark> apostolicam prosecuti fuerunt; de quibus etiam Beatdo Sua...","fid":"letterContent"}]}]}