{"stem":"sexcento","instances":[{"docId":"A057","docUri":"A057.html","score":2,"contexts":[{"form":"sexcentos","weight":"1","pos":47,"context":"...diebus in defensionem illorum confinium ducentos equites leves et <mark>sexcentos<\/mark> pedites pixidarios et cuspidarios, ut saltim excursiones que...","fid":"letterContent"},{"form":"sexcentos","weight":"1","pos":139,"context":"...diebus in defensionem illorum confinium ducentos equites leves et <mark>sexcentos<\/mark> pedites pixidarios et cuspidarios, ut saltim excursiones que...","fid":"letterContent"}]}]}