{"stem":"utmost","instances":[{"docId":"A252","docUri":"A252.html","score":1,"contexts":[{"form":"utmost","weight":"1","pos":148,"context":"...with the Turks only possible in the face of <mark>utmost<\/mark> danger. 8. Thanks him for sending Georg of...","fid":"letterContent"}]},{"docId":"A057","docUri":"A057.html","score":1,"contexts":[{"form":"utmost","weight":"1","pos":158,"context":"...Urges L, for his part, to do his <mark>utmost<\/mark> to help exhausted Croatia with just as many or...","fid":"letterContent"}]}]}