{"stem":"valoir","instances":[{"docId":"A192","docUri":"A192.html","score":1,"contexts":[{"form":"valoir","weight":"1","pos":104,"context":"...vous seroit escheute. L’on dit aussi qu’elle doit <mark>valoir<\/mark> bien cent mil florins d’or ou ducatz par an...","fid":"letterContent"}]},{"docId":"A056","docUri":"A056.html","score":1,"contexts":[{"form":"valoir","weight":"1","pos":1160,"context":"...cas necessaires et accoustumées et vaille ce que pourra <mark>valoir<\/mark> ou temps advenir avec l’execution que mad. armée...","fid":"letterContent"}]}]}