{"stem":"veit","instances":[{"docId":"A018","docUri":"A018.html","score":1,"contexts":[{"form":"Veit","weight":"1","pos":1104,"context":"...Den geheimen Nachrichtendienst aus der Schweiz nach Österreich hat <mark>Veit<\/mark> Sutor geleitet. Vgl. Nr. A21 [13]. Ein...","fid":"letterContent"}]},{"docId":"A026","docUri":"A026.html","score":1,"contexts":[{"form":"Veit","weight":"1","pos":2961,"context":"...F an Doktor Jakob Stürtzl den Befehl, dem <mark>Veit<\/mark> Sutor, der „auf kuntschafften und practiken in der...","fid":"letterContent"}]},{"docId":"A021","docUri":"A021.html","score":1,"contexts":[{"form":"Veit","weight":"1","pos":2816,"context":"13] Gemeint ist der kaiserliche Sekretär <mark>Veit<\/mark> Sutor, der vorher schon im Solde K’s bei...","fid":"letterContent"}]}]}