{"stem":"verschiden","instances":[{"docId":"A036","docUri":"A036.html","score":2,"contexts":[{"form":"verschiden","weight":"1","pos":2071,"context":"...erobert sei, Franntz von Sickingen dornnstags darnach mit toud <mark>verschiden<\/mark> und allso zuganngen, das durch ain schuts ain...","fid":"letterContent"},{"form":"verschiden","weight":"1","pos":2128,"context":"...und daruf weitter nit mer geredt sonnder onlanng darnach <mark>verschiden<\/mark>. (Wien, St.-A., Württembergica 1, Orig.)...","fid":"letterContent"}]}]}