{"stem":"werdemberg","instances":[{"docId":"A122","docUri":"A122.html","score":1,"contexts":[{"form":"Werdemberg","weight":"1","pos":202,"context":"...deux filles qu’il maria avec les contes Felix de <mark>Werdemberg<\/mark> et Guillaume de Furstemberg, comme bien vous tiens...","fid":"letterContent"}]},{"docId":"A152","docUri":"A152.html","score":1,"contexts":[{"form":"Werdemberg","weight":"1","pos":329,"context":"...jadis seigneur de Belvoir, et la contesse de <mark>Werdemberg<\/mark>. Si le plaisir dud. sr empereur estoit...","fid":"letterContent"}]}]}