{"stem":"zeitschr","instances":[{"docId":"A187","docUri":"A187.html","score":1,"contexts":[{"form":"Zeitschr","weight":"1","pos":928,"context":"...an den Verhandlungen des Augsburger Generallandtages K. Mayr, <mark>Zeitschr<\/mark>. des Ferdinandeums, 3. Folge 38, S. 126...","fid":"letterContent"}]},{"docId":"A080","docUri":"A080.html","score":1,"contexts":[{"form":"Zeitschr","weight":"1","pos":491,"context":"...verschiedene diesbezügliche Bemerkungen bei J. Weizsäcker, Hist. <mark>Zeitschr<\/mark>. 64 (1890), S. 199—215...","fid":"letterContent"}]},{"docId":"A018","docUri":"A018.html","score":1,"contexts":[{"form":"Zeitschr","weight":"1","pos":1175,"context":"...Reorganisation dieses Regiments. Vgl. W. Beemelmans in <mark>Zeitschr<\/mark>. für die Gesch. des Oberrheins 22 (...","fid":"letterContent"}]},{"docId":"A134","docUri":"A134.html","score":1,"contexts":[{"form":"Zeitschr","weight":"1","pos":231,"context":"...v. Borries, Über Franz' I. Gefangennahme. Deutsche <mark>Zeitschr<\/mark>. f. Geschichtsw. 6, S. 371. —...","fid":"letterContent"}]},{"docId":"A094","docUri":"A094.html","score":1,"contexts":[{"form":"Zeitschr","weight":"1","pos":62,"context":"Druck: Teilweise bei Baumgarten, Deutsche <mark>Zeitschr<\/mark>. f. Gesch. 2, S. 10. Familienkorrespondenz Bd....","fid":"letterContent"}]},{"docId":"A156","docUri":"A156.html","score":1,"contexts":[{"form":"Zeitschr","weight":"1","pos":407,"context":"...Beratungen begannen am 12. Dezember. M. Mayr, <mark>Zeitschr<\/mark>. des Ferdinandeums, 3. Folge 38, S. 22....","fid":"letterContent"}]}]}